LICENSE
coingecko_api_client/__init__.py
coingecko_api_client/client.py
coingecko_api_client-0.1.6.dist-info/LICENSE
coingecko_api_client-0.1.6.dist-info/WHEEL
coingecko_api_client-0.1.6.dist-info/METADATA
coingecko_api_client-0.1.6.dist-info/RECORD
