Metadata-Version: 2.1
Name: coingecko-api-client
Version: 0.1.6
Summary: Unofficial CoinGecko API client based on HTTPX
Home-page: https://github.com/eserdk/coingecko-api-client
License: MIT
Keywords: coingecko,api,client,crypto
Author: Eugene Serdyuk
Author-email: eugene.serdyuk@pm.me
Requires-Python: >=3.8,<4.0
Classifier: Development Status :: 2 - Pre-Alpha
Classifier: Intended Audience :: Developers
Classifier: License :: OSI Approved :: MIT License
Classifier: Operating System :: OS Independent
Classifier: Programming Language :: Python :: 3
Classifier: Programming Language :: Python :: 3 :: Only
Classifier: Programming Language :: Python :: 3.8
Classifier: Programming Language :: Python :: 3.9
Requires-Dist: httpx (>=0.18.2,<0.19.0)
Project-URL: Repository, https://github.com/eserdk/coingecko-api-client
